AgainML/KMeans.py
AgainML/KNN.py
AgainML/LinearRegression.py
AgainML/__init__.py
AgainML/mean_shift.py
AgainML/svm.py
AgainML-0.1.1.dist-info/LICENSE
AgainML-0.1.1.dist-info/METADATA
AgainML-0.1.1.dist-info/WHEEL
AgainML-0.1.1.dist-info/top_level.txt
AgainML-0.1.1.dist-info/RECORD
