Metadata-Version: 2.1
Name: AgainML
Version: 0.1.1
Summary: Machine Learning Algorithms implemented from scratch in Python
Home-page: https://github.com/NotShrirang/Machine-Learning-from-Scratch
Author: Shrirang Mahajan
Author-email: shrirangmahajan123@gmail.com
Project-URL: Bug Tracker, https://github.com/NotShrirang/Machine-Learning-from-Scratch/issues
Classifier: Programming Language :: Python :: 3
Classifier: License :: OSI Approved :: MIT License
Classifier: Operating System :: OS Independent
Requires-Python: >=3.6
License-File: LICENSE
